fonadalabs/__init__.py
fonadalabs/asr/__init__.py
fonadalabs/asr/client.py
fonadalabs/asr/config.py
fonadalabs/asr/exceptions.py
fonadalabs/asr/languages.py
fonadalabs/asr/utils.py
fonadalabs/asr/ws_client.py
fonadalabs/asr/models/__init__.py
fonadalabs/asr/models/types.py
fonadalabs/denoise/__init__.py
fonadalabs/denoise/exceptions.py
fonadalabs/denoise/http_client.py
fonadalabs/denoise/streaming_client.py
fonadalabs/tts/__init__.py
fonadalabs/tts/client.py
fonadalabs-2.1.3.dist-info/licenses/LICENSE
fonadalabs-2.1.3.dist-info/METADATA
fonadalabs-2.1.3.dist-info/WHEEL
fonadalabs-2.1.3.dist-info/top_level.txt
fonadalabs-2.1.3.dist-info/RECORD
