Metadata-Version: 2.4
Name: fonadalabs
Version: 2.1.3
Summary: Unified Python SDK for FonadaLabs Text-to-Speech, Automatic Speech Recognition, and Audio Denoising APIs
Author-email: FonadaLabs <support@fonadalabs.com>
License: MIT
Project-URL: Homepage, https://github.com/fonadalabs/fonadalabs-sdk
Project-URL: Documentation, https://github.com/fonadalabs/fonadalabs-sdk#readme
Project-URL: Repository, https://github.com/fonadalabs/fonadalabs-sdk
Project-URL: Bug Tracker, https://github.com/fonadalabs/fonadalabs-sdk/issues
Keywords: text-to-speech,speech-recognition,audio-denoising,tts,asr,denoise,fonadalabs,speech,audio,ai,machine-learning
Classifier: Development Status :: 4 - Beta
Classifier: Intended Audience :: Developers
Classifier: License :: OSI Approved :: MIT License
Classifier: Operating System :: OS Independent
Classifier: Programming Language :: Python :: 3
Classifier: Programming Language :: Python :: 3.9
Classifier: Programming Language :: Python :: 3.10
Classifier: Programming Language :: Python :: 3.11
Classifier: Programming Language :: Python :: 3.12
Classifier: Topic :: Software Development :: Libraries :: Python Modules
Classifier: Topic :: Multimedia :: Sound/Audio :: Speech
Classifier: Topic :: Scientific/Engineering :: Artificial Intelligence
Requires-Python: >=3.9
License-File: LICENSE
Requires-Dist: httpx<1.0,>=0.24
Requires-Dist: websockets<13,>=11
Requires-Dist: loguru<1.0,>=0.7
Requires-Dist: requests<3.0,>=2.28
Requires-Dist: numpy<2.0,>=1.24.0
Requires-Dist: soundfile<0.14,>=0.12
Requires-Dist: librosa<1.0,>=0.10
Requires-Dist: websocket-client<2.0,>=1.5
Provides-Extra: dev
Requires-Dist: pytest<8.0,>=7.0; extra == "dev"
Requires-Dist: black<24.0,>=23.0; extra == "dev"
Requires-Dist: isort<6.0,>=5.0; extra == "dev"
Requires-Dist: python-dotenv<2.0,>=1.0; extra == "dev"
Requires-Dist: nest-asyncio<2.0,>=1.5; extra == "dev"
Requires-Dist: build>=0.10.0; extra == "dev"
Requires-Dist: twine>=4.0.0; extra == "dev"
Dynamic: license-file
